tap_indeedsponsoredjobs/__init__.py
tap_indeedsponsoredjobs/auth.py
tap_indeedsponsoredjobs/client.py
tap_indeedsponsoredjobs/streams.py
tap_indeedsponsoredjobs/tap.py
tap_indeedsponsoredjobs/tests/__init__.py
tap_indeedsponsoredjobs/tests/test_core.py
tap_indeed-0.0.24.dist-info/METADATA
tap_indeed-0.0.24.dist-info/WHEEL
tap_indeed-0.0.24.dist-info/entry_points.txt
tap_indeed-0.0.24.dist-info/RECORD
