Metadata-Version: 2.1
Name: tap-indeed
Version: 0.0.24
Summary: `tap-indeed` is a Singer tap for IndeedSponsoredJobs, built with the Meltano SDK for Singer Taps.
Home-page: https://github.com/AutoIDM/tap-indeed
License: Apache 2.0
Keywords: ELT,IndeedSponsoredJobs,tap-indeed,Indeed,singer-sdk,meltano
Author: AutoIDM
Requires-Python: >=3.7.1,<3.11
Classifier: License :: Other/Proprietary License
Classifier: Programming Language :: Python :: 3
Classifier: Programming Language :: Python :: 3.8
Classifier: Programming Language :: Python :: 3.9
Classifier: Programming Language :: Python :: 3.10
Requires-Dist: backoff (>=2.2.0,<3.0.0)
Requires-Dist: cloudscraper (==1.2.64)
Requires-Dist: requests (>=2.25.1,<3.0.0)
Requires-Dist: singer-sdk (>=0.21.0,<0.22.0)
Project-URL: Repository, https://github.com/AutoIDM/tap-indeed
